{"last_node_id":21,"last_link_id":20,"nodes":[{"id":14,"type":"ADE_LoopedUniformContextOptions","pos":[557.0900453396607,-368.7370525781249],"size":{"0":317.4000244140625,"1":246},"flags":{},"order":0,"mode":0,"inputs":[{"name":"prev_context","type":"CONTEXT_OPTIONS","link":null},{"name":"view_opts","type":"VIEW_OPTS","link":null}],"outputs":[{"name":"CONTEXT_OPTS","type":"CONTEXT_OPTIONS","links":[12],"shape":3}],"properties":{"Node name for S&R":"ADE_LoopedUniformContextOptions"},"widgets_values":[16,1,4,false,"pyramid",false,0,1]},{"id":4,"type":"CheckpointLoaderSimple","pos":[100.21139275085451,530.5251613798525],"size":{"0":315,"1":98},"flags":{},"order":1,"mode":0,"outputs":[{"name":"MODEL","type":"MODEL","links":[13],"slot_index":0},{"name":"CLIP","type":"CLIP","links":[5,15],"slot_index":1},{"name":"VAE","type":"VAE","links":[],"slot_index":2}],"properties":{"Node name for S&R":"CheckpointLoaderSimple"},"widgets_values":["sd15\\Juggernaut.safetensors"],"color":"#571a1a","bgcolor":"#6b2e2e"},{"id":15,"type":"VAELoader","pos":[105.45297098304707,683.2572357701877],"size":{"0":315,"1":58},"flags":{},"order":2,"mode":0,"outputs":[{"name":"VAE","type":"VAE","links":[18],"shape":3,"slot_index":0}],"properties":{"Node name for S&R":"VAELoader"},"widgets_values":["vae-ft-mse-840000-ema-pruned.safetensors"],"color":"#571a1a","bgcolor":"#6b2e2e"},{"id":12,"type":"ADE_EmptyLatentImageLarge","pos":[84.9187866082764,47.279213117542355],"size":{"0":315,"1":106},"flags":{},"order":3,"mode":0,"outputs":[{"name":"LATENT","type":"LATENT","links":[11],"shape":3}],"properties":{"Node name for S&R":"ADE_EmptyLatentImageLarge"},"widgets_values":[512,512,30],"color":"#1a572e","bgcolor":"#2e6b42"},{"id":17,"type":"Note","pos":[89.21139275085451,202.52516137985225],"size":[375.565185546875,285.2653364701704],"flags":{},"order":4,"mode":0,"properties":{"text":""},"widgets_values":["The Batch Prompt Schedule designed for efficiency managing and scheduling complex prompts across a series of frames or iterations. It enables creators to dynamically adjust text and parameters over time, allowing for detailed control in animation and other time-based media projects."],"color":"#57431a","bgcolor":"#6b572e"},{"id":13,"type":"ADE_AnimateDiffLoaderGen1","pos":[938.182166383667,-384.83202742263785],"size":{"0":315,"1":222},"flags":{},"order":8,"mode":0,"inputs":[{"name":"model","type":"MODEL","link":13},{"name":"context_options","type":"CONTEXT_OPTIONS","link":12,"slot_index":1},{"name":"motion_lora","type":"MOTION_LORA","link":null},{"name":"ad_settings","type":"AD_SETTINGS","link":null},{"name":"ad_keyframes","type":"AD_KEYFRAMES","link":null},{"name":"sample_settings","type":"SAMPLE_SETTINGS","link":null},{"name":"scale_multival","type":"MULTIVAL","link":null},{"name":"effect_multival","type":"MULTIVAL","link":null}],"outputs":[{"name":"MODEL","type":"MODEL","links":[14],"shape":3,"slot_index":0}],"properties":{"Node name for S&R":"ADE_AnimateDiffLoaderGen1"},"widgets_values":["v3_sd15_mm.ckpt","sqrt_linear (AnimateDiff)"],"color":"#571a1a","bgcolor":"#6b2e2e"},{"id":3,"type":"KSampler","pos":[1020,230],"size":{"0":315,"1":262},"flags":{},"order":11,"mode":0,"inputs":[{"name":"model","type":"MODEL","link":14},{"name":"positive","type":"CONDITIONING","link":16},{"name":"negative","type":"CONDITIONING","link":6},{"name":"latent_image","type":"LATENT","link":17}],"outputs":[{"name":"LATENT","type":"LATENT","links":[7],"slot_index":0}],"properties":{"Node name for S&R":"KSampler"},"widgets_values":[495557979845502,"randomize",20,5,"dpmpp_2m","karras",1],"color":"#57571a","bgcolor":"#6b6b2e"},{"id":8,"type":"VAEDecode","pos":[1360,230],"size":{"0":210,"1":46},"flags":{},"order":12,"mode":0,"inputs":[{"name":"samples","type":"LATENT","link":7},{"name":"vae","type":"VAE","link":18}],"outputs":[{"name":"IMAGE","type":"IMAGE","links":[10,19],"slot_index":0}],"properties":{"Node name for S&R":"VAEDecode"},"color":"#2e571a","bgcolor":"#426b2e"},{"id":11,"type":"VHS_VideoCombine","pos":[1610,210],"size":[315,527],"flags":{},"order":13,"mode":0,"inputs":[{"name":"images","type":"IMAGE","link":10},{"name":"audio","type":"VHS_AUDIO","link":null},{"name":"batch_manager","type":"VHS_BatchManager","link":null}],"outputs":[{"name":"Filenames","type":"VHS_FILENAMES","links":null,"shape":3}],"properties":{"Node name for S&R":"VHS_VideoCombine"},"widgets_values":{"frame_rate":8,"loop_count":0,"filename_prefix":"AnimateDiff","format":"image/gif","pingpong":false,"save_output":true,"videopreview":{"hidden":false,"paused":false,"params":{"filename":"AnimateDiff_00285.gif","subfolder":"","type":"output","format":"image/gif"}}}},{"id":10,"type":"BatchPromptScheduleLatentInput","pos":[481.2113927508544,-3.4748386201476804],"size":[411.7484332095818,607.629509856061],"flags":{},"order":10,"mode":0,"inputs":[{"name":"clip","type":"CLIP","link":15},{"name":"num_latents","type":"LATENT","link":11,"slot_index":1}],"outputs":[{"name":"POS","type":"CONDITIONING","links":[16],"shape":3,"slot_index":0},{"name":"NEG","type":"CONDITIONING","links":null,"shape":3},{"name":"INPUT_LATENTS","type":"LATENT","links":[17],"shape":3,"slot_index":2}],"properties":{"Node name for S&R":"BatchPromptScheduleLatentInput"},"widgets_values":["\"0\" :\"A peaceful forest scene\",\n\"15\" :\"The forest scene becomes dark and ominous\"",false,"masterpiece, best quality, natural lighting, photorealistic, high contrast","",0,0,0,0,0],"color":"#1a572e","bgcolor":"#2e6b42"},{"id":19,"type":"FILM VFI","pos":[1732,-35],"size":{"0":443.4000244140625,"1":126},"flags":{},"order":14,"mode":0,"inputs":[{"name":"frames","type":"IMAGE","link":19},{"name":"optional_interpolation_states","type":"INTERPOLATION_STATES","link":null}],"outputs":[{"name":"IMAGE","type":"IMAGE","links":[20],"shape":3,"slot_index":0}],"properties":{"Node name for S&R":"FILM VFI"},"widgets_values":["film_net_fp32.pt",10,2]},{"id":21,"type":"Note","pos":[1725,-263],"size":[450.472966974432,177.00817801735616],"flags":{},"order":5,"mode":0,"properties":{"text":""},"widgets_values":["FILM VFI enhance the smoothness of existing video footage by creating additional frames in between the original frames. This effectively increase the frame rate, resulting a more fluid visual experience."],"color":"#57431a","bgcolor":"#6b572e"},{"id":7,"type":"CLIPTextEncode","pos":[473.5039952899169,658.5251613798526],"size":{"0":425.27801513671875,"1":180.6060791015625},"flags":{},"order":9,"mode":0,"inputs":[{"name":"clip","type":"CLIP","link":5}],"outputs":[{"name":"CONDITIONING","type":"CONDITIONING","links":[6],"slot_index":0}],"properties":{"Node name for S&R":"CLIPTextEncode"},"widgets_values":["text, watermark"],"color":"#572e1a","bgcolor":"#6b422e"},{"id":16,"type":"Note","pos":[83,-310],"size":[364.2777182839133,210.87061101740056],"flags":{},"order":6,"mode":0,"properties":{"text":""},"widgets_values":["Empty Latent Image (Big Batch) generates a batch of empty latent images. these images contain no visual information but hold a specific format compatible with samplers in ComfyUI."],"color":"#57431a","bgcolor":"#6b572e"},{"id":18,"type":"Note","pos":[1291,-422],"size":[293.47445401278424,174.442832253196],"flags":{},"order":7,"mode":0,"properties":{"text":""},"widgets_values":["To learn about the usage and how to download AnimateDiff models, please refer to our previous tutorials."],"color":"#57431a","bgcolor":"#6b572e"},{"id":20,"type":"VHS_VideoCombine","pos":[2226,205],"size":[315,527],"flags":{},"order":15,"mode":0,"inputs":[{"name":"images","type":"IMAGE","link":20},{"name":"audio","type":"VHS_AUDIO","link":null},{"name":"batch_manager","type":"VHS_BatchManager","link":null}],"outputs":[{"name":"Filenames","type":"VHS_FILENAMES","links":null,"shape":3}],"properties":{"Node name for S&R":"VHS_VideoCombine"},"widgets_values":{"frame_rate":8,"loop_count":0,"filename_prefix":"AnimateDiff","format":"image/gif","pingpong":false,"save_output":true,"videopreview":{"hidden":false,"paused":false,"params":{"filename":"AnimateDiff_00286.gif","subfolder":"","type":"output","format":"image/gif"}}}}],"links":[[5,4,1,7,0,"CLIP"],[6,7,0,3,2,"CONDITIONING"],[7,3,0,8,0,"LATENT"],[10,8,0,11,0,"IMAGE"],[11,12,0,10,1,"LATENT"],[12,14,0,13,1,"CONTEXT_OPTIONS"],[13,4,0,13,0,"MODEL"],[14,13,0,3,0,"MODEL"],[15,4,1,10,0,"CLIP"],[16,10,0,3,1,"CONDITIONING"],[17,10,2,3,3,"LATENT"],[18,15,0,8,1,"VAE"],[19,8,0,19,0,"IMAGE"],[20,19,0,20,0,"IMAGE"]],"groups":[{"title":"RAW Images","bounding":[1010,136,925,611],"color":"#3f789e","font_size":24},{"title":"Checkpoint & Prompts","bounding":[75,-77,834,927],"color":"#3f789e","font_size":24},{"title":"AnimateDiff Nodes","bounding":[547,-459,716,346],"color":"#3f789e","font_size":24},{"title":"Txt2Vid with Prompt Scheduling","bounding":[563,-598,864,80],"color":"#a1309b","font_size":60}],"config":{},"extra":{"ds":{"scale":0.4665073802097335,"offset":[-1.4938909667587836,798.5769794227888]}},"version":0.4}